sri_tool/__init__.py
sri_tool/cli.py
sri_tool/generator.py
sri_tool/utils.py
sri_tool/validator.py
sri_tool-1.0.1.dist-info/licenses/LICENSE
sri_tool-1.0.1.dist-info/METADATA
sri_tool-1.0.1.dist-info/WHEEL
sri_tool-1.0.1.dist-info/entry_points.txt
sri_tool-1.0.1.dist-info/top_level.txt
sri_tool-1.0.1.dist-info/RECORD
