Metadata-Version: 2.4
Name: sri-tool
Version: 1.0.1
Summary: A CLI tool for managing Subresource Integrity (SRI) hashes in HTML files - no external dependencies!
Home-page: https://github.com/adasThePro/sri-tool
Author: adasThePro
License-Expression: MIT
Project-URL: Homepage, https://github.com/adasThePro/sri-tool
Project-URL: Repository, https://github.com/adasThePro/sri-tool
Project-URL: Issues, https://github.com/adasThePro/sri-tool/issues
Keywords: python,sri,subresource-integrity,web-security,cli,hash,validator,generator,integrity,assets
Classifier: Operating System :: OS Independent
Classifier: Development Status :: 5 - Production/Stable
Classifier: Intended Audience :: Developers
Classifier: Topic :: Software Development :: Build Tools
Classifier: Topic :: Security
Classifier: Topic :: Internet :: WWW/HTTP
Classifier: Programming Language :: Python :: 3
Classifier: Programming Language :: Python :: 3.6
Classifier: Programming Language :: Python :: 3.7
Classifier: Programming Language :: Python :: 3.8
Classifier: Programming Language :: Python :: 3.9
Classifier: Programming Language :: Python :: 3.10
Classifier: Programming Language :: Python :: 3.11
Classifier: Programming Language :: Python :: 3.12
Classifier: Programming Language :: Python :: 3.13
Classifier: Programming Language :: Python :: 3.14
Classifier: Programming Language :: Python :: 3.15
Requires-Python: >=3.6
License-File: LICENSE
Provides-Extra: dev
Requires-Dist: pytest>=6.0.0; extra == "dev"
Requires-Dist: pytest-cov>=2.10.0; extra == "dev"
Dynamic: home-page
Dynamic: license-file
Dynamic: requires-python
